{
  "usuarios": [
    {
      "id": 1,
      "nombre": "Juan Carlos",
      "apellido": "Delgado Delgadillo",
      "email": "juan@gmail.com",
      "fecha_nacimiento": "1985-03-15",
      "nro_carnet": "123456789",
      "lugar_nacimiento": "Santa Cruz de la Sierra",
      "domicilio": "Av. San Martin 456, Santa Cruz",
      "ocupacion": "Ingeniero de Software",
      "estado_civil": "Casado"
    },
    {
      "id": 2,
      "nombre": "JOSE HUMBERTO",
      "apellido": "CASTRO ORTIZ",
      "email": "jose@gmail.com",
      "fecha_nacimiento": "1990-06-22",
      "nro_carnet": "987654321",
      "lugar_nacimiento": "Cochabamba",
      "domicilio": "Calle 7, Cochabamba",
      "ocupacion": "Médico",
      "estado_civil": "Soltero"
    },
    {
      "id": 3,
      "nombre": "Maria Teresa",
      "apellido": "Lopez Perez",
      "email": "maria@gmail.com",
      "fecha_nacimiento": "1995-12-10",
      "nro_carnet": "345678901",
      "lugar_nacimiento": "La Paz",
      "domicilio": "Calle 10, La Paz",
      "ocupacion": "Abogada",
      "estado_civil": "Casada"
    },
    {
      "id": 4,
      "nombre": "Carlos Eduardo",
      "apellido": "Reyes Salazar",
      "email": "carlos@gmail.com",
      "fecha_nacimiento": "1982-02-14",
      "nro_carnet": "654321987",
      "lugar_nacimiento": "Sucre",
      "domicilio": "Av. Pando 123, Sucre",
      "ocupacion": "Contador",
      "estado_civil": "Divorciado"
    },
    {
      "id": 5,
      "nombre": "Ana Lucia",
      "apellido": "Gomez Martinez",
      "email": "ana@gmail.com",
      "fecha_nacimiento": "1991-04-18",
      "nro_carnet": "112233445",
      "lugar_nacimiento": "Oruro",
      "domicilio": "Calle 3, Oruro",
      "ocupacion": "Arquitecta",
      "estado_civil": "Soltera"
    },
    {
      "id": 6,
      "nombre": "Carlos Andres",
      "apellido": "Paredes Rojas",
      "email": "carlos.andres@gmail.com",
      "fecha_nacimiento": "1988-01-30",
      "nro_carnet": "556677889",
      "lugar_nacimiento": "Potosí",
      "domicilio": "Calle Bolivia 456, Potosí",
      "ocupacion": "Profesor de Matemáticas",
      "estado_civil": "Casado"
    },
    {
      "id": 7,
      "nombre": "Sofia Marcela",
      "apellido": "Cortez Vargas",
      "email": "sofia@gmail.com",
      "fecha_nacimiento": "1994-09-03",
      "nro_carnet": "998877665",
      "lugar_nacimiento": "Tarija",
      "domicilio": "Calle Juana Azurduy 789, Tarija",
      "ocupacion": "Diseñadora Gráfica",
      "estado_civil": "Soltera"
    },
    {
      "id": 8,
      "nombre": "Fernando Javier",
      "apellido": "Fernandez Cruz",
      "email": "fernando@gmail.com",
      "fecha_nacimiento": "1992-10-25",
      "nro_carnet": "223344556",
      "lugar_nacimiento": "Cochabamba",
      "domicilio": "Calle 14, Cochabamba",
      "ocupacion": "Ingeniero Civil",
      "estado_civil": "Casado"
    },
    {
      "id": 9,
      "nombre": "Patricia Beatriz",
      "apellido": "Gutierrez Morales",
      "email": "patricia@gmail.com",
      "fecha_nacimiento": "1996-08-10",
      "nro_carnet": "667788990",
      "lugar_nacimiento": "Santa Cruz",
      "domicilio": "Calle Beni 101, Santa Cruz",
      "ocupacion": "Psicóloga",
      "estado_civil": "Soltera"
    },
    {
      "id": 10,
      "nombre": "Manuel Antonio",
      "apellido": "Rodriguez Flores",
      "email": "manuel@gmail.com",
      "fecha_nacimiento": "1987-11-12",
      "nro_carnet": "443322110",
      "lugar_nacimiento": "La Paz",
      "domicilio": "Calle 25 de Mayo 222, La Paz",
      "ocupacion": "Músico",
      "estado_civil": "Casado"
    },
    {
      "id": 11,
      "nombre": "Gabriela Marisol",
      "apellido": "Sanchez Silva",
      "email": "gabriela@gmail.com",
      "fecha_nacimiento": "1993-05-08",
      "nro_carnet": "112233456",
      "lugar_nacimiento": "Sucre",
      "domicilio": "Calle Avaroa 789, Sucre",
      "ocupacion": "Maestra",
      "estado_civil": "Soltera"
    },
    {
      "id": 12,
      "nombre": "Victor Hugo",
      "apellido": "Zamora Guzman",
      "email": "victor@gmail.com",
      "fecha_nacimiento": "1984-03-22",
      "nro_carnet": "223344667",
      "lugar_nacimiento": "Oruro",
      "domicilio": "Av. 6 de Octubre 345, Oruro",
      "ocupacion": "Abogado",
      "estado_civil": "Divorciado"
    },
    {
      "id": 13,
      "nombre": "Lucia Mercedes",
      "apellido": "Mendoza Lopez",
      "email": "lucia.m@gmail.com",
      "fecha_nacimiento": "1989-02-14",
      "nro_carnet": "778899667",
      "lugar_nacimiento": "Tarija",
      "domicilio": "Calle El Alto 567, Tarija",
      "ocupacion": "Contadora",
      "estado_civil": "Soltera"
    },
    {
      "id": 14,
      "nombre": "Santiago Elias",
      "apellido": "Villanueva Morales",
      "email": "santiago@gmail.com",
      "fecha_nacimiento": "1990-07-17",
      "nro_carnet": "889900776",
      "lugar_nacimiento": "Potosí",
      "domicilio": "Calle Independencia 123, Potosí",
      "ocupacion": "Economista",
      "estado_civil": "Casado"
    },
    {
      "id": 15,
      "nombre": "Ricardo Alberto",
      "apellido": "Torres Silva",
      "email": "ricardo@gmail.com",
      "fecha_nacimiento": "1992-04-11",
      "nro_carnet": "667788112",
      "lugar_nacimiento": "Cochabamba",
      "domicilio": "Calle 25 de Mayo 301, Cochabamba",
      "ocupacion": "Chef",
      "estado_civil": "Soltero"
    },
    {
      "id": 16,
      "nombre": "Valentina Isabel",
      "apellido": "Chavez Flores",
      "email": "valentina@gmail.com",
      "fecha_nacimiento": "1995-01-05",
      "nro_carnet": "556677443",
      "lugar_nacimiento": "La Paz",
      "domicilio": "Calle Los Andes 233, La Paz",
      "ocupacion": "Fotógrafa",
      "estado_civil": "Soltera"
    },
    {
      "id": 17,
      "nombre": "Felipe Javier",
      "apellido": "Guerrero Perez",
      "email": "felipe@gmail.com",
      "fecha_nacimiento": "1983-11-28",
      "nro_carnet": "998877665",
      "lugar_nacimiento": "Santa Cruz",
      "domicilio": "Calle La Paz 89, Santa Cruz",
      "ocupacion": "Programador",
      "estado_civil": "Casado"
    },
    {
      "id": 18,
      "nombre": "Martina Lucia",
      "apellido": "Solis Rios",
      "email": "martina@gmail.com",
      "fecha_nacimiento": "1997-09-17",
      "nro_carnet": "445566778",
      "lugar_nacimiento": "Sucre",
      "domicilio": "Calle Ayacucho 111, Sucre",
      "ocupacion": "Estilista",
      "estado_civil": "Soltera"
    },
    {
      "id": 19,
      "nombre": "Jose Luis",
      "apellido": "Quispe Choque",
      "email": "joseluis@gmail.com",
      "fecha_nacimiento": "1986-06-30",
      "nro_carnet": "667788999",
      "lugar_nacimiento": "Oruro",
      "domicilio": "Calle Vinto 332, Oruro",
      "ocupacion": "Arquitecto",
      "estado_civil": "Casado"
    },
    {
      "id": 20,
      "nombre": "Isabel Cristina",
      "apellido": "Luna Mejia",
      "email": "isabel@gmail.com",
      "fecha_nacimiento": "1998-08-21",
      "nro_carnet": "998877554",
      "lugar_nacimiento": "Cochabamba",
      "domicilio": "Calle Capinota 453, Cochabamba",
      "ocupacion": "Psicóloga",
      "estado_civil": "Soltera"
    },
    {
      "id": 21,
      "nombre": "Paola Beatriz",
      "apellido": "Molina Ramos",
      "email": "paola@gmail.com",
      "fecha_nacimiento": "1991-12-03",
      "nro_carnet": "667788333",
      "lugar_nacimiento": "Santa Cruz",
      "domicilio": "Calle La Virgen 324, Santa Cruz",
      "ocupacion": "Maestra",
      "estado_civil": "Divorciada"
    },
    {
      "id": 22,
      "nombre": "Emilia Gabriela",
      "apellido": "Cabrera Vargas",
      "email": "emilia@gmail.com",
      "fecha_nacimiento": "1984-10-17",
      "nro_carnet": "112233445",
      "lugar_nacimiento": "La Paz",
      "domicilio": "Calle San Pedro 567, La Paz",
      "ocupacion": "Chef",
      "estado_civil": "Soltera"
    },
    {
      "id": 23,
      "nombre": "Hector Julio",
      "apellido": "Serrano Guzman",
      "email": "hector@gmail.com",
      "fecha_nacimiento": "1992-01-14",
      "nro_carnet": "223344556",
      "lugar_nacimiento": "Tarija",
      "domicilio": "Calle Salta 134, Tarija",
      "ocupacion": "Profesor",
      "estado_civil": "Casado"
    },
    {
      "id": 24,
      "nombre": "Cecilia Isabel",
      "apellido": "Gonzalez Perez",
      "email": "cecilia@gmail.com",
      "fecha_nacimiento": "1994-02-23",
      "nro_carnet": "556677889",
      "lugar_nacimiento": "Sucre",
      "domicilio": "Calle Arequipa 332, Sucre",
      "ocupacion": "Ingeniera Industrial",
      "estado_civil": "Soltera"
    },
    {
      "id": 25,
      "nombre": "Eduardo Santiago",
      "apellido": "Diaz Herrera",
      "email": "eduardo@gmail.com",
      "fecha_nacimiento": "1980-07-10",
      "nro_carnet": "998877661",
      "lugar_nacimiento": "Potosí",
      "domicilio": "Calle Colon 876, Potosí",
      "ocupacion": "Abogado",
      "estado_civil": "Soltero"
    },
    {
      "id": 26,
      "nombre": "Olga Lidia",
      "apellido": "Perez Vasquez",
      "email": "olga@gmail.com",
      "fecha_nacimiento": "1990-12-05",
      "nro_carnet": "223344113",
      "lugar_nacimiento": "Oruro",
      "domicilio": "Calle Loayza 234, Oruro",
      "ocupacion": "Farmacéutica",
      "estado_civil": "Divorciada"
    },
    {
      "id": 27,
      "nombre": "Luis Alberto",
      "apellido": "Valverde Arce",
      "email": "luis@gmail.com",
      "fecha_nacimiento": "1985-01-29",
      "nro_carnet": "667788112",
      "lugar_nacimiento": "La Paz",
      "domicilio": "Calle Tupac Katari 587, La Paz",
      "ocupacion": "Psicólogo",
      "estado_civil": "Soltero"
    },
    {
      "id": 28,
      "nombre": "Nadia Karina",
      "apellido": "Loza Cordero",
      "email": "nadia@gmail.com",
      "fecha_nacimiento": "1995-09-12",
      "nro_carnet": "112233667",
      "lugar_nacimiento": "Cochabamba",
      "domicilio": "Calle La Paz 679, Cochabamba",
      "ocupacion": "Comunicadora",
      "estado_civil": "Soltera"
    },
    {
      "id": 29,
      "nombre": "Antonio Marcos",
      "apellido": "Salazar Fernandez",
      "email": "antonio@gmail.com",
      "fecha_nacimiento": "1990-04-18",
      "nro_carnet": "223344998",
      "lugar_nacimiento": "Tarija",
      "domicilio": "Calle El Alto 678, Tarija",
      "ocupacion": "Economista",
      "estado_civil": "Casado"
    },
    {
      "id": 30,
      "nombre": "Maria Cristina",
      "apellido": "Vargas Cordero",
      "email": "maria@gmail.com",
      "fecha_nacimiento": "1992-11-30",
      "nro_carnet": "445566880",
      "lugar_nacimiento": "Sucre",
      "domicilio": "Calle Santa Cruz 123, Sucre",
      "ocupacion": "Ingeniera Electrónica",
      "estado_civil": "Soltera"
    }
  ]
}
